pancircs-0.2.1.dist-info/METADATA
pancircs-0.2.1.dist-info/RECORD
pancircs-0.2.1.dist-info/top_level.txt
pancircs-0.2.1.dist-info/metadata.json
pancircs-0.2.1.dist-info/DESCRIPTION.rst
pancircs-0.2.1.dist-info/WHEEL
pancircs/utils.py
pancircs/val_circs.py
pancircs/__init__.py
pancircs/patch_circs.py
pancircs/conn_circs.py
