Metadata-Version: 2.0
Name: pancircs
Version: 0.2.1
Summary: Package for circualar visualization of data in pandas
Home-page: http://github.com/cimbi/pancircs
Author: Jan Cimbalnik
Author-email: jan.cimbalnik@fnusa.cz, jan.cimbalnik@mayo.edu
License: BSD 3.0
Keywords: pandas circle visualization
Platform: UNKNOWN
Classifier: Development Status :: 2 - Pre-Alpha
Classifier: Intended Audience :: Science/Research
Classifier: License :: OSI Approved :: BSD License
Classifier: Programming Language :: Python :: 3.4
Classifier: Topic :: Scientific/Engineering :: Visualization
Requires-Dist: pandas
Requires-Dist: matplotlib
